CHANGELOG.md
LICENSE
MANIFEST.in
Makefile
README.md
setup.cfg
setup.py
tox.ini
px_pipeline/__init__.py
px_pipeline/exceptions.py
px_pipeline/filters.py
px_pipeline/pipelines.py
px_pipeline/runner.py
px_pipeline/utils.py
px_pipeline.egg-info/PKG-INFO
px_pipeline.egg-info/SOURCES.txt
px_pipeline.egg-info/dependency_links.txt
px_pipeline.egg-info/requires.txt
px_pipeline.egg-info/top_level.txt
tests/test_context_unwrapper.py
tests/test_filter.py
tests/test_straight_pipeline.py